{
  "phase": "implement",
  "steps_completed": [
    {
      "step": 1,
      "task": "Create test file with imports (vitest, @testing-library/react, AnalyticsSummaryCards, formatCurrency, MarketAnalyticsSummary type)",
      "files_created": ["frontend/src/__tests__/AnalyticsSummaryCards.test.tsx"],
      "files_modified": [],
      "verified": true
    },
    {
      "step": 2,
      "task": "Write test: renders all four card labels (Total Activity, Total Volume, Unique Traders, Last Update)",
      "files_created": [],
      "files_modified": ["frontend/src/__tests__/AnalyticsSummaryCards.test.tsx"],
      "verified": true
    },
    {
      "step": 3,
      "task": "Write test: renders correctly formatted values via toLocaleString() and formatCurrency()",
      "files_created": [],
      "files_modified": ["frontend/src/__tests__/AnalyticsSummaryCards.test.tsx"],
      "verified": true
    },
    {
      "step": 4,
      "task": "Write test: renders the Last Update caption text",
      "files_created": [],
      "files_modified": ["frontend/src/__tests__/AnalyticsSummaryCards.test.tsx"],
      "verified": true
    },
    {
      "step": 5,
      "task": "Write test: handles zero values (totalTrades=0, totalVolume=0, uniqueTraders=0)",
      "files_created": [],
      "files_modified": ["frontend/src/__tests__/AnalyticsSummaryCards.test.tsx"],
      "verified": true
    },
    {
      "step": 6,
      "task": "Write test: handles large numbers (millions volume, thousands trades/traders)",
      "files_created": [],
      "files_modified": ["frontend/src/__tests__/AnalyticsSummaryCards.test.tsx"],
      "verified": true
    },
    {
      "step": 7,
      "task": "Run vitest on new test file — all 5 tests pass",
      "files_created": [],
      "files_modified": [],
      "verified": true
    }
  ],
  "all_steps_done": true
}
